linkml_renderer/__init__.py
linkml_renderer/cli.py
linkml_renderer/paths/__init__.py
linkml_renderer/paths/context.py
linkml_renderer/paths/html_context.py
linkml_renderer/renderers/__init__.py
linkml_renderer/renderers/html_renderer.py
linkml_renderer/renderers/markdown_renderer.py
linkml_renderer/renderers/mermaid_renderer.py
linkml_renderer/renderers/renderer.py
linkml_renderer/style/__init__.py
linkml_renderer/style/model.py
linkml_renderer/style/model.yaml
linkml_renderer/style/style_engine.py
linkml_renderer-0.3.1.dist-info/LICENSE
linkml_renderer-0.3.1.dist-info/METADATA
linkml_renderer-0.3.1.dist-info/WHEEL
linkml_renderer-0.3.1.dist-info/entry_points.txt
linkml_renderer-0.3.1.dist-info/RECORD
