Metadata-Version: 2.1
Name: linkml-renderer
Version: 0.3.1
Summary: linkml-renderer
License: Apache Software License 2.0
Author: Harshad Hegde
Author-email: hhegde@lbl.gov
Requires-Python: >=3.8,<4.0
Classifier: License :: Other/Proprietary License
Classifier: Programming Language :: Python :: 3
Classifier: Programming Language :: Python :: 3.8
Classifier: Programming Language :: Python :: 3.9
Classifier: Programming Language :: Python :: 3.10
Classifier: Programming Language :: Python :: 3.11
Classifier: Programming Language :: Python :: 3.12
Provides-Extra: docs
Requires-Dist: airium (>=0.2.5,<0.3.0)
Requires-Dist: click (>=8.1.3,<9.0.0)
Requires-Dist: linkml-runtime (>=1.4.1)
Requires-Dist: pydantic
